cf_extension_core/__init__.py
cf_extension_core/__init__.pyi
cf_extension_core/base_handler.py
cf_extension_core/base_handler.pyi
cf_extension_core/constants.py
cf_extension_core/constants.pyi
cf_extension_core/custom_resource_helpers.py
cf_extension_core/custom_resource_helpers.pyi
cf_extension_core/dynamo_table_creator.py
cf_extension_core/dynamo_table_creator.pyi
cf_extension_core/interface.py
cf_extension_core/interface.pyi
cf_extension_core/py.typed
cf_extension_core/resource_base.py
cf_extension_core/resource_base.pyi
cf_extension_core/resource_create.py
cf_extension_core/resource_create.pyi
cf_extension_core/resource_delete.py
cf_extension_core/resource_delete.pyi
cf_extension_core/resource_list.py
cf_extension_core/resource_list.pyi
cf_extension_core/resource_read.py
cf_extension_core/resource_read.pyi
cf_extension_core/resource_update.py
cf_extension_core/resource_update.pyi
cf_extension_core-0.2.7.dist-info/METADATA
cf_extension_core-0.2.7.dist-info/WHEEL
cf_extension_core-0.2.7.dist-info/RECORD
