Metadata-Version: 2.1
Name: cf_extension_core
Version: 0.2.7
Summary: Provides common functionality for Custom resources in CloudFormation.
License: MIT
Author: Nick Carpenter
Requires-Python: >=3.8.1,<4.0.0
Classifier: License :: OSI Approved :: MIT License
Classifier: Programming Language :: Python :: 3
Classifier: Programming Language :: Python :: 3.9
Classifier: Programming Language :: Python :: 3.10
Classifier: Programming Language :: Python :: 3.11
Requires-Dist: boto3 (>=1.26.50,<2.0.0)
Requires-Dist: cloudformation-cli-python-lib (>=2.1.17,<3.0.0)
Requires-Dist: cryptography (>=41.0.4,<42.0.0)
